CHANGES.rst
CONTRIBUTORS.rst
MANIFEST.in
README.rst
setup.py
docs/LICENSE.GPL
docs/LICENSE.txt
src/interlegis/__init__.py
src/interlegis.portalmodelo.policy.egg-info/PKG-INFO
src/interlegis.portalmodelo.policy.egg-info/SOURCES.txt
src/interlegis.portalmodelo.policy.egg-info/dependency_links.txt
src/interlegis.portalmodelo.policy.egg-info/entry_points.txt
src/interlegis.portalmodelo.policy.egg-info/namespace_packages.txt
src/interlegis.portalmodelo.policy.egg-info/not-zip-safe
src/interlegis.portalmodelo.policy.egg-info/requires.txt
src/interlegis.portalmodelo.policy.egg-info/top_level.txt
src/interlegis/portalmodelo/__init__.py
src/interlegis/portalmodelo/policy/__init__.py
src/interlegis/portalmodelo/policy/config.py
src/interlegis/portalmodelo/policy/configure.zcml
src/interlegis/portalmodelo/policy/cover.py
src/interlegis/portalmodelo/policy/interfaces.py
src/interlegis/portalmodelo/policy/overrides.zcml
src/interlegis/portalmodelo/policy/profiles.zcml
src/interlegis/portalmodelo/policy/setuphandlers.py
src/interlegis/portalmodelo/policy/testing.py
src/interlegis/portalmodelo/policy/utils.py
src/interlegis/portalmodelo/policy/browser/__init__.py
src/interlegis/portalmodelo/policy/browser/admin.py
src/interlegis/portalmodelo/policy/browser/configure.zcml
src/interlegis/portalmodelo/policy/browser/overrides.zcml
src/interlegis/portalmodelo/policy/browser/images/acesso-a-informacao-vertical.png
src/interlegis/portalmodelo/policy/browser/images/acesso-a-informacao.png
src/interlegis/portalmodelo/policy/browser/images/audio-player.png
src/interlegis/portalmodelo/policy/browser/images/bens.png
src/interlegis/portalmodelo/policy/browser/images/brasao-republica.png
src/interlegis/portalmodelo/policy/browser/images/brasil.png
src/interlegis/portalmodelo/policy/browser/images/camara-dos-deputados.png
src/interlegis/portalmodelo/policy/browser/images/carlos-drummond-de-andrade.jpg
src/interlegis/portalmodelo/policy/browser/images/clarice-lispector.jpg
src/interlegis/portalmodelo/policy/browser/images/congresso-nacional.png
src/interlegis/portalmodelo/policy/browser/images/entenda-a-lai.jpg
src/interlegis/portalmodelo/policy/browser/images/entenda-o-indice-de-transparencia.jpg
src/interlegis/portalmodelo/policy/browser/images/erico-verissimo.jpg
src/interlegis/portalmodelo/policy/browser/images/euclides-da-cunha.jpg
src/interlegis/portalmodelo/policy/browser/images/executivo.png
