Metadata-Version: 2.1
Name: interlegis.portalmodelo.policy
Version: 1.0rc14
Summary: Pacote de politicas do Portal Modelo.
Home-page: https://github.com/interlegis/interlegis.portalmodelo.policy
Author: Programa Interlegis
Author-email: ti@interlegis.leg.br
License: GPLv2
Keywords: interlegis portalmodelo egov plone brasil
Platform: UNKNOWN
Classifier: Development Status :: 4 - Beta
Classifier: Environment :: Web Environment
Classifier: Framework :: Plone
Classifier: Framework :: Plone :: 4.3
Classifier: Intended Audience :: System Administrators
Classifier: License :: OSI Approved :: GNU General Public License v2 (GPLv2)
Classifier: Operating System :: OS Independent
Classifier: Programming Language :: Python
Classifier: Programming Language :: Python :: 2.7
Classifier: Topic :: Software Development :: Libraries :: Python Modules
Provides-Extra: test
